aws_vapor/__init__.py
aws_vapor/configure.py
aws_vapor/downloader.py
aws_vapor/dsl.py
aws_vapor/generator.py
aws_vapor/main.py
aws_vapor/meta.py
aws_vapor/utils.py
aws_vapor-0.1.0.dist-info/METADATA
aws_vapor-0.1.0.dist-info/RECORD
aws_vapor-0.1.0.dist-info/WHEEL
aws_vapor-0.1.0.dist-info/entry_points.txt
aws_vapor-0.1.0.dist-info/top_level.txt
