Metadata-Version: 2.1
Name: aws-vapor
Version: 0.1.0
Summary: Generates AWS CloudFormation template from python object
Home-page: https://github.com/ohtomi/aws-vapor/
Author: Kenichi Ohtomi
Author-email: ohtomi.kenichi@gmail.com
License: MIT
Keywords: aws cloudformation template generator
Platform: UNKNOWN
Classifier: Development Status :: 4 - Beta
Classifier: Environment :: Console
Classifier: Intended Audience :: Developers
Classifier: License :: OSI Approved :: MIT License
Classifier: Operating System :: MacOS :: MacOS X
Classifier: Operating System :: Microsoft :: Windows
Classifier: Operating System :: POSIX
Classifier: Programming Language :: Python
Classifier: Programming Language :: Python :: 3.6
Requires-Dist: cliff
